prefect_snowflake/__init__.py
prefect_snowflake/_version.py
prefect_snowflake/credentials.py
prefect_snowflake/database.py
prefect_snowflake/experimental/workers/__init__.py
prefect_snowflake/experimental/workers/spcs.py
prefect_snowflake-0.28.7.dist-info/licenses/LICENSE
prefect_snowflake-0.28.7.dist-info/METADATA
prefect_snowflake-0.28.7.dist-info/WHEEL
prefect_snowflake-0.28.7.dist-info/entry_points.txt
prefect_snowflake-0.28.7.dist-info/top_level.txt
prefect_snowflake-0.28.7.dist-info/RECORD
